__init__.py
openspace_app/__init__.py
openspace_app/app.py
openspace_app/widgets.py
openspace_app/assets/__init__.py
openspace_app/assets/css/__init__.py
openspace_app/assets/img/__init__.py
openspace_app/pages/__init__.py
openspace_app/pages/cw.py
openspace_app/pages/hardware.py
openspace_app/pages/home.py
openspace_app/pages/inertial.py
openspace_app/pages/od.py
openspace_app-0.1.8.dist-info/LICENSE
openspace_app-0.1.8.dist-info/METADATA
openspace_app-0.1.8.dist-info/WHEEL
openspace_app-0.1.8.dist-info/top_level.txt
openspace_app-0.1.8.dist-info/RECORD
